rubigram/__init__.py
rubigram/client.py
rubigram/exceptions.py
rubigram/filters.py
rubigram/handlers.py
rubigram/network.py
rubigram/sync.py
rubigram/utils.py
rubigram/bot/__init__.py
rubigram/bot/bot.py
rubigram/bot/dict_like.py
rubigram/bot/enums.py
rubigram/bot/exceptions.py
rubigram/bot/filters.py
rubigram/bot/models.py
rubigram/crypto/__init__.py
rubigram/crypto/crypto.py
rubigram/enums/__init__.py
rubigram/enums/chat_access_type.py
rubigram/enums/chat_action.py
rubigram/enums/chat_type.py
rubigram/enums/message_media_type.py
rubigram/enums/parse_mode.py
rubigram/enums/poll_type.py
rubigram/enums/reaction_type.py
rubigram/enums/report_type.py
rubigram/methods/__init__.py
rubigram/methods/advanced/__init__.py
rubigram/methods/advanced/build.py
rubigram/methods/auth/__init__.py
rubigram/methods/auth/register_device.py
rubigram/methods/auth/send_code.py
rubigram/methods/auth/sign_in.py
rubigram/methods/bots/__init__.py
rubigram/methods/bots/delete_bot_chat.py
rubigram/methods/bots/get_bot_info.py
rubigram/methods/bots/stop_bot.py
rubigram/methods/channels/__init__.py
rubigram/methods/channels/add_channel.py
rubigram/methods/channels/add_channel_members.py
rubigram/methods/channels/ban_channel_member.py
rubigram/methods/channels/channel_preview_by_join_link.py
rubigram/methods/channels/check_channel_username.py
rubigram/methods/channels/create_channel_voice_chat.py
rubigram/methods/channels/delete_no_access_channel_chat.py
rubigram/methods/channels/discard_channel_voice_chat.py
rubigram/methods/channels/edit_channel_info.py
rubigram/methods/channels/get_banned_channel_members.py
rubigram/methods/channels/get_channel_admin_access_list.py
rubigram/methods/channels/get_channel_admin_members.py
rubigram/methods/channels/get_channel_all_members.py
rubigram/methods/channels/get_channel_info.py
rubigram/methods/channels/get_channel_link.py
rubigram/methods/channels/join_channel_action.py
rubigram/methods/channels/join_channel_by_link.py
rubigram_python-1.1.7.dist-info/licenses/LICENSE
rubigram_python-1.1.7.dist-info/METADATA
rubigram_python-1.1.7.dist-info/WHEEL
rubigram_python-1.1.7.dist-info/top_level.txt
rubigram_python-1.1.7.dist-info/RECORD
