Metadata-Version: 2.4
Name: rubigram-python
Version: 1.1.7
Summary: A fast and flexible rubika automation library
Home-page: https://github.com/yourusername/rubigram
Author: stone
Author-email: kissme.cloud@example.com
Classifier: Programming Language :: Python :: 3
Classifier: License :: OSI Approved :: MIT License
Classifier: Operating System :: OS Independent
Requires-Python: >=3.9
License-File: LICENSE
Requires-Dist: aiohttp
Requires-Dist: pycryptodome
Requires-Dist: aiofiles
Requires-Dist: markdownify
Requires-Dist: mutagen
Dynamic: author
Dynamic: author-email
Dynamic: classifier
Dynamic: description
Dynamic: description-content-type
Dynamic: home-page
Dynamic: license-file
Dynamic: requires-dist
Dynamic: requires-python
Dynamic: summary
